lonely_silhouette/__init__.py
lonely_silhouette/__main__.py
lonely_silhouette/font_converter.py
lonely_silhouette/lonely_silhouette_maker.py
lonely_silhouette/part_of_speech.py
lonely_silhouette-0.2.4.dist-info/METADATA
lonely_silhouette-0.2.4.dist-info/WHEEL
lonely_silhouette-0.2.4.dist-info/licenses/LICENSE
lonely_silhouette-0.2.4.dist-info/RECORD
