Metadata-Version: 2.4
Name: lonely-silhouette
Version: 0.2.4
Summary: いや待て、この孤独な𝑆𝑖𝑙ℎ𝑜𝑢𝑒𝑡𝑡𝑒は…？
Project-URL: homepage, https://github.com/otariidae/lonely_silhouette
Project-URL: source, https://github.com/otariidae/lonely_silhouette
Project-URL: bug tracker, https://github.com/otariidae/lonely_silhouette/issues
Project-URL: pypi, https://pypi.org/project/lonely-silhouette/
Author-email: otariidae <otariidae@users.noreply.github.com>
License: CC0-1.0
License-File: LICENSE
Classifier: Natural Language :: Japanese
Requires-Python: >=3.12
Requires-Dist: jaconv>=0.3.4
Requires-Dist: janome>=0.5.0
Requires-Dist: requests>=2.31.0
